smile_id_core/BusinessVerification.py
smile_id_core/IdApi.py
smile_id_core/ServerError.py
smile_id_core/Signature.py
smile_id_core/Utilities.py
smile_id_core/WebApi.py
smile_id_core/__init__.py
smile_id_core/base.py
smile_id_core/constants.py
smile_id_core/image_upload.py
smile_id_core/types.py
smile_id_core-3.0.1.dist-info/LICENSE
smile_id_core-3.0.1.dist-info/METADATA
smile_id_core-3.0.1.dist-info/WHEEL
smile_id_core-3.0.1.dist-info/RECORD
