Metadata-Version: 2.3
Name: smile-id-core
Version: 3.0.1
Summary: The official Smile Identity package exposes four classes namely; the WebApi class, the IDApi class, the Signature class and the Utilities class.
License: MIT
Author: Smile Identity
Author-email: support@usesmileid.com
Requires-Python: >=3.8,<4.0
Classifier: License :: OSI Approved :: MIT License
Classifier: Operating System :: OS Independent
Classifier: Programming Language :: Python :: 3
Classifier: Programming Language :: Python :: 3.8
Classifier: Programming Language :: Python :: 3.9
Classifier: Programming Language :: Python :: 3.10
Classifier: Programming Language :: Python :: 3.11
Classifier: Programming Language :: Python :: 3.12
Classifier: Programming Language :: Python :: 3.13
Requires-Dist: pycryptodome (>=3.0.0,<4.0.0)
Requires-Dist: requests (>=2.0.0,<3.0.0)
Requires-Dist: types-requests (>=2.0.0.0,<3.0.0.0)
Requires-Dist: typing-extensions (>=4.2.0,<5.0.0)
Project-URL: Homepage, https://github.com/smileidentity/smile-identity-core-python-3
